lbkit/__init__.py
lbkit/build_conan_parallel.py
lbkit/cli.py
lbkit/errors.py
lbkit/helper.py
lbkit/lbkit.py
lbkit/log.py
lbkit/misc.py
lbkit/tools.py
lbkit/ci_robot/__init__.py
lbkit/ci_robot/gitee.py
lbkit/codegen/__init__.py
lbkit/codegen/codegen.py
lbkit/codegen/ctype_defination.py
lbkit/codegen/idf_interface.py
lbkit/codegen/renderer.py
lbkit/codegen/template/client.c.mako
lbkit/codegen/template/client.h.mako
lbkit/codegen/template/interface.c.mako
lbkit/codegen/template/interface.introspect.xml.mako
lbkit/codegen/template/public.c.mako
lbkit/codegen/template/public.h.mako
lbkit/codegen/template/server.c.mako
lbkit/codegen/template/server.h.mako
lbkit/component/__init__.py
lbkit/component/arg_parser.py
lbkit/component/build.py
lbkit/component/test.py
lbkit/component/template/conanbase.mako
lbkit/component/template/deploy.mako
lbkit/tasks/__init__.py
lbkit/tasks/config.py
lbkit/tasks/executor.py
lbkit/tasks/task.py
lbkit/tasks/task_build_image.py
lbkit/tasks/task_build_manifest.py
lbkit/tasks/task_build_prepare.py
lbkit/tasks/task_build_rootfs.py
lbkit/tasks/task_download.py
lbkit/tasks/image_maker/__init__.py
lbkit/tasks/image_maker/make_image.py
lbkit/tasks/image_maker/make_qemu_image.py
lbkit/tasks/image_maker/make_rockchip_image.py
lbkit/tasks/template/conanfile.py.mako
lbkit/tasks/template/rootfs.py.mako
lbkit/ukr/__init__.py
lbkit/ukr/build.py
lbkit/utils/__init__.py
lbkit/utils/env_detector.py
lbkit/utils/images/__init__.py
lbkit/utils/images/emmc.py
lbkit-0.9.5.dist-info/licenses/AUTHORS
lbkit-0.9.5.dist-info/licenses/LICENSE
test/__init__.py
test/test_codegen.py
test/test_config.py
test/test_helper.py
lbkit-0.9.5.dist-info/METADATA
lbkit-0.9.5.dist-info/WHEEL
lbkit-0.9.5.dist-info/entry_points.txt
lbkit-0.9.5.dist-info/top_level.txt
lbkit-0.9.5.dist-info/RECORD
