Metadata-Version: 2.4
Name: lbkit
Version: 0.9.5
Summary: Tools provided by litebmc.com
Home-page: https://www.litebmc.com
Author: xuhj@litebmc.com
Author-email: xuhj@litebmc.com
Classifier: Programming Language :: Python :: 3
Classifier: License :: OSI Approved :: MIT License
Classifier: Operating System :: OS Independent
License-File: LICENSE
License-File: AUTHORS
Requires-Dist: pyyaml
Requires-Dist: colorama
Requires-Dist: mako
Requires-Dist: node-semver>=0.6.1
Requires-Dist: jsonschema
Requires-Dist: conan
Requires-Dist: requests
Requires-Dist: gitpython
Requires-Dist: inflection
Requires-Dist: meson>=1.4.0
Requires-Dist: psutil
Requires-Dist: loguru
Dynamic: author
Dynamic: author-email
Dynamic: classifier
Dynamic: description
Dynamic: description-content-type
Dynamic: home-page
Dynamic: license-file
Dynamic: requires-dist
Dynamic: summary
